sl_sources/__init__.py
sl_sources/__main__.py
sl_sources/audio_transcriber.py
sl_sources/crawl.py
sl_sources/doi.py
sl_sources/google.py
sl_sources/google_books.py
sl_sources/google_scholar.py
sl_sources/http.py
sl_sources/models.py
sl_sources/openalex.py
sl_sources/papers.py
sl_sources/podcasts.py
sl_sources/scrape.py
sl_sources/semantic_scholar.py
sl_sources/serialization.py
sl_sources/sources.py
sl_sources/twitter.py
sl_sources/user_agent.py
sl_sources/video.py
tests/__init__.py
tests/audio_transcriber_test.py
tests/crawl_test.py
tests/doi_test.py
tests/google_books_test.py
tests/google_scholar_test.py
tests/google_test.py
tests/http_test.py
tests/openalex_test.py
tests/papers_test.py
tests/podcasts_test.py
tests/scrape_test.py
tests/semantic_scholar_test.py
tests/sources_test.py
tests/video_test.py
sl_sources-0.0.14.dist-info/METADATA
sl_sources-0.0.14.dist-info/WHEEL
sl_sources-0.0.14.dist-info/top_level.txt
sl_sources-0.0.14.dist-info/RECORD
