Metadata-Version: 2.1
Name: sl_sources
Version: 0.0.14
Summary: Code for Society Library Sources
Home-page: https://github.com/SocietyLibrary/Sources
Author: SocietyLibrary
Author-email: info@societylibrary.org
License: Proprietary
Keywords: data sources
Classifier: Development Status :: 3 - Alpha
Classifier: License :: Other/Proprietary License
Classifier: Natural Language :: English
Classifier: Operating System :: OS Independent
Classifier: Programming Language :: Python
Classifier: Programming Language :: Python :: 3
Classifier: Programming Language :: Python :: 3 :: Only
Classifier: Programming Language :: Python :: 3.11
Classifier: Programming Language :: Python :: 3.12
Classifier: Intended Audience :: Developers
Classifier: Intended Audience :: Science/Research
Classifier: Topic :: Scientific/Engineering
Requires-Python: >=3.11
Requires-Dist: aiohttp >=3.9.5
Requires-Dist: pypdf >=4.3.1
Requires-Dist: Requests >=2.32.3
Requires-Dist: tqdm >=4.66.4
Requires-Dist: pybtex >=0.24.0
Requires-Dist: twikit >=2.1.0
Requires-Dist: pyalex >=0.14
Requires-Dist: youtube-search2 >=2.1.7
Requires-Dist: python-dotenv >=1.0.1
Requires-Dist: yt-dlp >=2024.8.1
Requires-Dist: playwright >=1.45.1
Requires-Dist: transformers >=4.44.1
Requires-Dist: huggingface-hub >=0.24.5
Requires-Dist: librosa >=0.10.2
Requires-Dist: flask >=2.3.3
Requires-Dist: functions-framework >=3.4.0
Requires-Dist: playwright-stealth >=1.0.6
Requires-Dist: capsolver-extension-python >=1.0.3
Requires-Dist: pydantic >=2.8.2
Requires-Dist: torch >=2.4.0
Requires-Dist: waybackpy >=3.0.6
Requires-Dist: torchvision >=0.19.0
Requires-Dist: podcast-api >=1.1.6
Requires-Dist: aiofiles >=23.2.1
Requires-Dist: pytest >=8.2.2
Requires-Dist: pytest-asyncio >=0.23.8
Requires-Dist: pytest-xdist >=3.6.1
Requires-Dist: sl-ai-models >=0.0.14
Requires-Dist: aiolimiter >=1.1.0
Requires-Dist: python-Levenshtein >=0.25.1
Requires-Dist: tenacity >=8.5.0
